short_lived_tokens/django/__init__.py
short_lived_tokens/short_lived_tokens/VERSION
short_lived_tokens-0.1.2.dist-info/LICENSE
short_lived_tokens-0.1.2.dist-info/METADATA
short_lived_tokens-0.1.2.dist-info/WHEEL
short_lived_tokens-0.1.2.dist-info/top_level.txt
short_lived_tokens-0.1.2.dist-info/RECORD
