Metadata-Version: 2.1
Name: short-lived-tokens
Version: 0.1.2
Summary: Short lived tokens v0.1.2
Home-page: https://github.com/FriedBotStudio/short_lived_tokens
Author: Tushar Srivastava
Author-email: tusharsrivastava@friedbotstudio.com
License: UNKNOWN
Project-URL: Bug Tracker, https://github.com/FriedBotStudio/short_lived_tokens/issues
Platform: UNKNOWN
Classifier: Development Status :: 4 - Beta
Classifier: Intended Audience :: Developers
Classifier: Programming Language :: Python :: 3
Classifier: Framework :: Django
Classifier: License :: OSI Approved :: MIT License
Classifier: Operating System :: OS Independent
Requires-Python: >=3.6
Requires-Dist: typing-extensions
Requires-Dist: pycryptodome
